{"type":"FeatureCollection","features":[{"type":"Feature","geometry":{"coordinates":[-73.518017,10.939074],"type":"Point"},"properties":{"title":"Ubicacion 3","description":"Maecenas enim erat, vestibulum quis purus sit amet, convallis porta nisl. Nulla ultrices tincidunt eros vulputate tempor. Praesent ac erat eu justo volutpat ullamcorper sit amet nec leo. Vestibulum tincidunt, sapien a auctor mattis, dui justo consectetur augue, sed molestie ligula lorem nec lacus. Phasellus tempor eu orci nec faucibus. Vestibulum consequat tellus eu libero hendrerit vestibulum. Duis vitae sodales ipsum, eget condimentum mauris. In vitae vestibulum quam, vitae venenatis velit. Aliquam in venenatis metus. Sed consequat nulla ut pharetra scelerisque. Cras et vestibulum mauris, et volutpat est. Nunc malesuada laoreet diam. In pellentesque, neque a commodo luctus, est ligula varius leo, eu aliquam quam mauris nec diam. Nunc rhoncus volutpat ex, sed commodo diam porttitor ut.","image":{"id":"30l7gnmutl09qo2n","w":1200,"h":535,"tip_color":"#383a5c","avg_color":"#7e8298","caption":null},"marker-color":"#1b8893"},"id":577487683}]}